{"learner":{"attributes":{"scikit_learn":"{\"_estimator_type\": \"classifier\"}"},"feature_names":[],"feature_types":[],"gradient_booster":{"model":{"cats":{"enc":[],"feature_segments":[],"sorted_idx":[]},"gbtree_model_param":{"num_parallel_tree":"1","num_trees":"100"},"iteration_indptr":[0,1,2,3,4,5,6,7,8,9,10,11,12,13,14,15,16,17,18,19,20,21,22,23,24,25,26,27,28,29,30,31,32,33,34,35,36,37,38,39,40,41,42,43,44,45,46,47,48,49,50,51,52,53,54,55,56,57,58,59,60,61,62,63,64,65,66,67,68,69,70,71,72,73,74,75,76,77,78,79,80,81,82,83,84,85,86,87,88,89,90,91,92,93,94,95,96,97,98,99,100],"tree_info":[0,0,0,0,0,0,0,0,0,0,0,0,0,0,0,0,0,0,0,0,0,0,0,0,0,0,0,0,0,0,0,0,0,0,0,0,0,0,0,0,0,0,0,0,0,0,0,0,0,0,0,0,0,0,0,0,0,0,0,0,0,0,0,0,0,0,0,0,0,0,0,0,0,0,0,0,0,0,0,0,0,0,0,0,0,0,0,0,0,0,0,0,0,0,0,0,0,0,0,0],"trees":[{"base_weights":[4.994983E-2,-1.532243E0,8.180158E-1,-4.8219632E-2,-1.9038902E-1,1.1509748E-1,-3.417239E-2],"categories":[],"categories_nodes":[],"categories_segments":[],"categories_sizes":[],"default_left":[0,0,0,0,0,0,0],"id":0,"left_children":[1,3,5,-1,-1,-1,-1],"loss_changes":[1.4558312E1,6.1406994E-1,3.4911547E0,0E0,0E0,0E0,0E0],"parents":[2147483647,0,0,1,1,2,2],"right_children":[2,4,6,-1,-1,-1,-1],"split_conditions":[5.542857E0,1.5806939E1,2E1,-4.8219632E-2,-1.9038902E-1,1.1509748E-1,-3.417239E-2],"split_indices":[9,10,4,0,0,0,0],"split_type":[0,0,0,0,0,0,0],"sum_hessian":[9.948486E0,2.9260254E0,7.022461E0,1.3654785E0,1.5605469E0,5.461914E0,1.5605469E0],"tree_param":{"num_deleted":"0","num_feature":"11","num_nodes":"7","size_leaf_vector":"1"}},{"base_weights":[-1.4654279E-2,-1.6904025E-1,7.8014207E-1,1.11266255E-1,-3.1765018E-2],"categories":[],"categories_nodes":[],"categories_segments":[],"categories_sizes":[],"default_left":[0,0,0,0,0],"id":1,"left_children":[1,-1,3,-1,-1],"loss_changes":[1.5241445E1,0E0,3.1914968E0,0E0,0E0],"parents":[2147483647,0,0,2,2],"right_children":[2,-1,4,-1,-1],"split_conditions":[4.142857E0,-1.6904025E-1,2E1,1.11266255E-1,-3.1765018E-2],"split_indices":[9,0,4,0,0],"split_type":[0,0,0,0,0],"sum_hessian":[9.453424E0,2.6787379E0,6.774687E0,5.1893044E0,1.5853823E0],"tree_param":{"num_deleted":"0","num_feature":"11","num_nodes":"5","size_leaf_vector":"1"}},{"base_weights":[-1.4210752E-1,-1.7982051E-1,5.9633243E-1,-1.89424E-2,8.943524E-1,1.0016703E-1,2.614191E-2],"categories":[],"categories_nodes":[],"categories_segments":[],"categories_sizes":[],"default_left":[0,0,0,0,0,0,0],"id":2,"left_children":[1,-1,3,-1,5,-1,-1],"loss_changes":[1.2749849E1,0E0,1.8917556E0,0E0,1.12229824E-1,0E0,0E0],"parents":[2147483647,0,0,2,2,4,4],"right_children":[2,-1,4,-1,6,-1,-1],"split_conditions":[2.8285713E0,-1.7982051E-1,2.2033347E2,-1.89424E-2,2.4757143E1,1.0016703E-1,2.614191E-2],"split_indices":[9,0,10,0,9,0,0],"split_type":[0,0,0,0,0,0,0],"sum_hessian":[8.548818E0,2.193753E0,6.355065E0,1.8477354E0,4.5073295E0,3.3557558E0,1.1515737E0],"tree_param":{"num_deleted":"0","num_feature":"11","num_nodes":"7","size_leaf_vector":"1"}},{"base_weights":[-1.17568895E-1,-1.4382217E0,1.0883438E-1,-1.9440609E-1,-4.811773E-1,3.6333177E-2,-1.1371819E-1],"categories":[],"categories_nodes":[],"categories_segments":[],"categories_sizes":[],"default_left":[0,0,0,0,0,0,0],"id":3,"left_children":[1,3,-1,-1,5,-1,-1],"loss_changes":[1.9974583E1,1.9440298E0,0E0,0E0,2.2888145E0,0E0,0E0],"parents":[2147483647,0,0,1,1,4,4],"right_children":[2,4,-1,-1,6,-1,-1],"split_conditions":[1.2E1,0E0,1.0883438E-1,-1.9440609E-1,7.8E0,3.6333177E-2,-1.1371819E-1],"split_indices":[0,0,0,0,0,0,0],"split_type":[0,0,0,0,0,0,0],"sum_hessian":[1.0559336E1,4.947953E0,5.6113825E0,2.5623324E0,2.3856206E0,1.23801E0,1.1476107E0],"tree_param":{"num_deleted":"0","num_feature":"11","num_nodes":"7","size_leaf_vector":"1"}},{"base_weights":[-2.4488147E-1,-1.3771827E0,1.0431625E-1,-1.7480153E-1,-6.227109E-1,3.738631E-2,-1.311085E-1],"categories":[],"categories_nodes":[],"categories_segments":[],"categories_sizes":[],"default_left":[0,0,0,0,0,0,0],"id":4,"left_children":[1,3,-1,-1,5,-1,-1],"loss_changes":[1.7520782E1,6.741028E-1,0E0,0E0,2.9800236E0,0E0,0E0],"parents":[2147483647,0,0,1,1,4,4],"right_children":[2,4,-1,-1,6,-1,-1],"split_conditions":[2.15E1,0E0,1.0431625E-1,-1.7480153E-1,6.5E0,3.738631E-2,-1.311085E-1],"split_indices":[0,0,0,0,0,0,0],"split_type":[0,0,0,0,0,0,0],"sum_hessian":[1.0028226E1,5.299928E0,4.728297E0,2.6704805E0,2.6294477E0,1.260902E0,1.3685455E0],"tree_param":{"num_deleted":"0","num_feature":"11","num_nodes":"7","size_leaf_vector":"1"}},{"base_weights":[-5.8090754E-2,-9.315173E-1,1.0156343E-1,-1.5451784E-1,-2.4115384E-1,4.2129967E-1,-1.2323041E-1,1.7993901E-3,6.756254E-2],"categories":[],"categories_nodes":[],"categories_segments":[],"categories_sizes":[],"default_left":[0,0,0,0,0,0,0,0,0],"id":5,"left_children":[1,3,-1,-1,5,7,-1,-1,-1],"loss_changes":[1.1840729E1,2.5622468E0,0E0,0E0,3.437711E0,3.375587E-1,0E0,0E0,0E0],"parents":[2147483647,0,0,1,1,4,4,5,5],"right_children":[2,4,-1,-1,6,8,-1,-1,-1],"split_conditions":[2.15E1,0E0,1.0156343E-1,-1.5451784E-1,7E0,1.99E1,-1.2323041E-1,1.7993901E-3,6.756254E-2],"split_indices":[0,0,0,0,4,8,0,0,0],"split_type":[0,0,0,0,0,0,0,0,0],"sum_hessian":[1.0616994E1,5.927602E0,4.6893916E0,2.4826102E0,3.4449918E0,2.409498E0,1.0354939E0,1.3459165E0,1.0635816E0],"tree_param":{"num_deleted":"0","num_feature":"11","num_nodes":"9","size_leaf_vector":"1"}},{"base_weights":[-8.255372E-2,-1.1295139E0,9.9213846E-2,-5.102092E-4,-1.439993E-1],"categories":[],"categories_nodes":[],"categories_segments":[],"categories_sizes":[],"default_left":[0,0,0,0,0],"id":6,"left_children":[1,3,-1,-1,-1],"loss_changes":[1.2121862E1,1.8849025E0,0E0,0E0,0E0],"parents":[2147483647,0,0,1,1],"right_children":[2,4,-1,-1,-1],"split_conditions":[1.2E1,1.4582449E1,9.9213846E-2,-5.102092E-4,-1.439993E-1],"split_indices":[0,10,0,0,0],"split_type":[0,0,0,0,0],"sum_hessian":[8.777481E0,4.4202666E0,4.3572145E0,1.1763833E0,3.2438831E0],"tree_param":{"num_deleted":"0","num_feature":"11","num_nodes":"5","size_leaf_vector":"1"}},{"base_weights":[-2.8107516E-2,-7.9656625E-1,9.485894E-2,-1.3155566E-1,-1.6595097E-1,7.9735346E-2,-8.951678E-2],"categories":[],"categories_nodes":[],"categories_segments":[],"categories_sizes":[],"default_left":[0,0,0,0,0,0,0],"id":7,"left_children":[1,3,-1,-1,5,-1,-1],"loss_changes":[8.289268E0,1.7981248E0,0E0,0E0,3.4714835E0,0E0,0E0],"parents":[2147483647,0,0,1,1,4,4],"right_children":[2,4,-1,-1,6,-1,-1],"split_conditions":[2.15E1,0E0,9.485894E-2,-1.3155566E-1,7.8E0,7.9735346E-2,-8.951678E-2],"split_indices":[0,0,0,0,0,0,0],"split_type":[0,0,0,0,0,0,0],"sum_hessian":[9.037494E0,5.161157E0,3.8763363E0,2.2353437E0,2.9258137E0,1.220319E0,1.7054945E0],"tree_param":{"num_deleted":"0","num_feature":"11","num_nodes":"7","size_leaf_vector":"1"}},{"base_weights":[2.6527095E-1,-1.0503627E-1,6.822917E-1,8.814149E-1,-1.7917348E-2,1.648551E-2,9.958797E-2],"categories":[],"categories_nodes":[],"categories_segments":[],"categories_sizes":[],"default_left":[0,0,0,0,0,0,0],"id":8,"left_children":[1,-1,3,5,-1,-1,-1],"loss_changes":[5.445247E0,0E0,1.3845074E0,3.2605934E-1,0E0,0E0,0E0],"parents":[2147483647,0,0,2,2,3,3],"right_children":[2,-1,4,6,-1,-1,-1],"split_conditions":[-2E-1,-1.0503627E-1,1.6E1,9E-1,-1.7917348E-2,1.648551E-2,9.958797E-2],"split_indices":[0,0,2,2,0,0,0],"split_type":[0,0,0,0,0,0,0],"sum_hessian":[7.6186514E0,1.4681482E0,6.150503E0,4.976949E0,1.173554E0,1.0216373E0,3.955312E0],"tree_param":{"num_deleted":"0","num_feature":"11","num_nodes":"7","size_leaf_vector":"1"}},{"base_weights":[-2.4050348E-1,-8.960505E-1,8.8139735E-2,-1.2669037E-1,-3.4619284E-1,2.8060868E-2,-1.07391655E-1],"categories":[],"categories_nodes":[],"categories_segments":[],"categories_sizes":[],"default_left":[0,0,0,0,0,0,0],"id":9,"left_children":[1,3,-1,-1,5,-1,-1],"loss_changes":[8.097513E0,9.4141865E-1,0E0,0E0,2.1723852E0,0E0,0E0],"parents":[2147483647,0,0,1,1,4,4],"right_children":[2,4,-1,-1,6,-1,-1],"split_conditions":[2.15E1,0E0,8.8139735E-2,-1.2669037E-1,7E0,2.8060868E-2,-1.07391655E-1],"split_indices":[0,0,0,0,4,0,0],"split_type":[0,0,0,0,0,0,0],"sum_hessian":[8.936297E0,5.7675333E0,3.1687644E0,2.6656318E0,3.1019015E0,1.996598E0,1.1053036E0],"tree_param":{"num_deleted":"0","num_feature":"11","num_nodes":"7","size_leaf_vector":"1"}},{"base_weights":[-1.2196719E-1,-8.0826986E-1,6.797574E-1,-1.41070215E-2,-9.2376494E-1,-4.6509015E-3,8.9654736E-2,-1.1082716E-1,-4.1060477E-2],"categories":[],"categories_nodes":[],"categories_segments":[],"categories_sizes":[],"default_left":[0,0,0,0,0,0,0,0,0],"id":10,"left_children":[1,3,5,-1,7,-1,-1,-1,-1],"loss_changes":[6.343355E0,3.4207153E-1,8.918865E-1,0E0,2.2647858E-2,0E0,0E0,0E0,0E0],"parents":[2147483647,0,0,1,1,2,2,4,4],"right_children":[2,4,6,-1,8,-1,-1,-1,-1],"split_conditions":[2.2033347E2,8.57102E0,9E-1,-1.41070215E-2,3E0,-4.6509015E-3,8.9654736E-2,-1.1082716E-1,-4.1060477E-2],"split_indices":[10,10,2,0,7,0,0,0,0],"split_type":[0,0,0,0,0,0,0,0,0],"sum_hessian":[9.530094E0,5.130259E0,4.399835E0,1.0848227E0,4.0454364E0,1.1919975E0,3.2078373E0,2.1225684E0,1.9228679E0],"tree_param":{"num_deleted":"0","num_feature":"11","num_nodes":"9","size_leaf_vector":"1"}},{"base_weights":[-1.5747795E-1,-7.7715874E-1,8.4630005E-2,-1.1168963E-1,-2.6189065E-1,3.12696E-2,-6.623534E-2],"categories":[],"categories_nodes":[],"categories_segments":[],"categories_sizes":[],"default_left":[0,0,0,0,0,0,0],"id":11,"left_children":[1,3,-1,-1,5,-1,-1],"loss_changes":[6.1695814E0,7.5785685E-1,0E0,0E0,1.0562943E0,0E0,0E0],"parents":[2147483647,0,0,1,1,4,4],"right_children":[2,4,-1,-1,6,-1,-1],"split_conditions":[2.15E1,0E0,8.4630005E-2,-1.1168963E-1,7.8E0,3.12696E-2,-6.623534E-2],"split_indices":[0,0,0,0,0,0,0],"split_type":[0,0,0,0,0,0,0],"sum_hessian":[7.8612194E0,5.0001507E0,2.8610687E0,2.3096802E0,2.6904702E0,1.1950164E0,1.495454E0],"tree_param":{"num_deleted":"0","num_feature":"11","num_nodes":"7","size_leaf_vector":"1"}},{"base_weights":[-1.1691889E-1,-8.540241E-1,8.642783E-2,-1.1366778E-1,4.292273E-3],"categories":[],"categories_nodes":[],"categories_segments":[],"categories_sizes":[],"default_left":[0,0,0,0,0],"id":12,"left_children":[1,3,-1,-1,-1],"loss_changes":[6.9420514E0,1.4181316E0,0E0,0E0,0E0],"parents":[2147483647,0,0,1,1],"right_children":[2,4,-1,-1,-1],"split_conditions":[2.15E1,4.31E1,8.642783E-2,-1.1366778E-1,4.292273E-3],"split_indices":[0,8,0,0,0],"split_type":[0,0,0,0,0],"sum_hessian":[7.577913E0,4.401204E0,3.1767087E0,3.1433654E0,1.2578386E0],"tree_param":{"num_deleted":"0","num_feature":"11","num_nodes":"5","size_leaf_vector":"1"}},{"base_weights":[-1.212743E-1,-6.517655E-1,5.557547E-1,-7.232822E-3,-7.862605E-1,-8.178191E-3,7.956965E-2,-9.789194E-2,-1.2599072E-2],"categories":[],"categories_nodes":[],"categories_segments":[],"categories_sizes":[],"default_left":[0,0,0,0,0,0,0,0,0],"id":13,"left_children":[1,3,5,-1,7,-1,-1,-1,-1],"loss_changes":[3.5004833E0,3.6079288E-1,7.348578E-1,0E0,4.1709185E-1,0E0,0E0,0E0,0E0],"parents":[2147483647,0,0,1,1,2,2,4,4],"right_children":[2,4,6,-1,8,-1,-1,-1,-1],"split_conditions":[2.2033347E2,8.57102E0,9E-1,-7.232822E-3,2.02E1,-8.178191E-3,7.956965E-2,-9.789194E-2,-1.2599072E-2],"split_indices":[10,10,2,0,2,0,0,0,0],"split_type":[0,0,0,0,0,0,0,0,0],"sum_hessian":[7.737831E0,4.359347E0,3.3784842E0,1.1109366E0,3.2484105E0,1.1040722E0,2.274412E0,2.1410673E0,1.1073432E0],"tree_param":{"num_deleted":"0","num_feature":"11","num_nodes":"9","size_leaf_vector":"1"}},{"base_weights":[-1.4213453E-1,-6.501937E-1,8.006754E-2,-1.0014635E-1,-2.2774573E-1,4.0382516E-2,-6.809578E-2],"categories":[],"categories_nodes":[],"categories_segments":[],"categories_sizes":[],"default_left":[0,0,0,0,0,0,0],"id":14,"left_children":[1,3,-1,-1,5,-1,-1],"loss_changes":[4.7414603E0,7.0352817E-1,0E0,0E0,1.461309E0,0E0,0E0],"parents":[2147483647,0,0,1,1,4,4],"right_children":[2,4,-1,-1,6,-1,-1],"split_conditions":[2.15E1,0E0,8.006754E-2,-1.0014635E-1,7.8E0,4.0382516E-2,-6.809578E-2],"split_indices":[0,0,0,0,0,0,0],"split_type":[0,0,0,0,0,0,0],"sum_hessian":[7.81177E0,5.2779613E0,2.5338087E0,2.1333985E0,3.1445627E0,1.3592956E0,1.7852671E0],"tree_param":{"num_deleted":"0","num_feature":"11","num_nodes":"7","size_leaf_vector":"1"}},{"base_weights":[-1.15823045E-1,-6.12884E-1,7.959973E-2,-1.1143996E-1,-2.7658397E-1,2.074597E-1,-9.52163E-2,-3.176309E-2,5.5599373E-2],"categories":[],"categories_nodes":[],"categories_segments":[],"categories_sizes":[],"default_left":[0,0,0,0,0,0,0,0,0],"id":15,"left_children":[1,3,-1,-1,5,7,-1,-1,-1],"loss_changes":[4.4433904E0,7.3971367E-1,0E0,0E0,1.8487448E0,8.6524093E-1,0E0,0E0,0E0],"parents":[2147483647,0,0,1,1,4,4,5,5],"right_children":[2,4,-1,-1,6,8,-1,-1,-1],"split_conditions":[2.15E1,1.4E0,7.959973E-2,-1.1143996E-1,1.14E1,4.4E0,-9.52163E-2,-3.176309E-2,5.5599373E-2],"split_indices":[0,2,0,0,2,0,0,0,0],"split_type":[0,0,0,0,0,0,0,0,0],"sum_hessian":[7.727432E0,5.213332E0,2.5140998E0,1.1639124E0,4.04942E0,2.7628143E0,1.2866054E0,1.1376029E0,1.6252114E0],"tree_param":{"num_deleted":"0","num_feature":"11","num_nodes":"9","size_leaf_vector":"1"}},{"base_weights":[-3.122689E-2,-4.642484E-1,7.5807385E-2,-1.0585194E-1,-8.085174E-2,-7.658707E-2,4.3749323E-1,7.662636E-2,-1.2650633E-2],"categories":[],"categories_nodes":[],"categories_segments":[],"categories_sizes":[],"default_left":[0,0,0,0,0,0,0,0,0],"id":16,"left_children":[1,3,-1,-1,5,-1,7,-1,-1],"loss_changes":[3.045221E0,1.2150872E0,0E0,0E0,1.9516131E0,0E0,6.95507E-1,0E0,0E0],"parents":[2147483647,0,0,1,1,4,4,6,6],"right_children":[2,4,-1,-1,6,-1,8,-1,-1],"split_conditions":[2.15E1,1.4E0,7.5807385E-2,-1.0585194E-1,-3.9E0,-7.658707E-2,1.13E1,7.662636E-2,-1.2650633E-2],"split_indices":[0,2,0,0,0,0,2,0,0],"split_type":[0,0,0,0,0,0,0,0,0],"sum_hessian":[6.8800797E0,4.708664E0,2.171416E0,1.155979E0,3.5526848E0,1.3246121E0,2.2280726E0,1.1810075E0,1.0470653E0],"tree_param":{"num_deleted":"0","num_feature":"11","num_nodes":"9","size_leaf_vector":"1"}},{"base_weights":[-1.3268468E-1,-6.1630476E-1,7.556828E-2,-7.741448E-2,-1.2414011E-2],"categories":[],"categories_nodes":[],"categories_segments":[],"categories_sizes":[],"default_left":[0,0,0,0,0],"id":17,"left_children":[1,3,-1,-1,-1],"loss_changes":[3.843497E0,3.421452E-1,0E0,0E0,0E0],"parents":[2147483647,0,0,1,1],"right_children":[2,4,-1,-1,-1],"split_conditions":[2.15E1,2.1E1,7.556828E-2,-7.741448E-2,-1.2414011E-2],"split_indices":[0,1,0,0,0],"split_type":[0,0,0,0,0],"sum_hessian":[6.861993E0,4.641466E0,2.2205265E0,3.0805705E0,1.5608958E0],"tree_param":{"num_deleted":"0","num_feature":"11","num_nodes":"5","size_leaf_vector":"1"}},{"base_weights":[-1.5464519E-1,-7.3628443E-1,7.537506E-2,-8.872178E-2,-2.437969E-2],"categories":[],"categories_nodes":[],"categories_segments":[],"categories_sizes":[],"default_left":[0,0,0,0,0],"id":18,"left_children":[1,3,-1,-1,-1],"loss_changes":[4.2555485E0,1.3869548E-1,0E0,0E0,0E0],"parents":[2147483647,0,0,1,1],"right_children":[2,4,-1,-1,-1],"split_conditions":[1.2E1,9E0,7.537506E-2,-8.872178E-2,-2.437969E-2],"split_indices":[0,2,0,0,0],"split_type":[0,0,0,0,0],"sum_hessian":[6.003905E0,3.7757723E0,2.2281325E0,2.2765665E0,1.4992057E0],"tree_param":{"num_deleted":"0","num_feature":"11","num_nodes":"5","size_leaf_vector":"1"}},{"base_weights":[1.13595895E-1,-7.775461E-2,4.7294208E-1,8.611735E-2,9.893858E-2,-5.893096E-2,6.761386E-2],"categories":[],"categories_nodes":[],"categories_segments":[],"categories_sizes":[],"default_left":[0,0,0,0,0,0,0],"id":19,"left_children":[1,-1,3,-1,5,-1,-1],"loss_changes":[2.6606407E0,0E0,7.4598205E-1,0E0,2.0055323E0,0E0,0E0],"parents":[2147483647,0,0,2,2,4,4],"right_children":[2,-1,4,-1,6,-1,-1],"split_conditions":[0E0,-7.775461E-2,9.528571E0,8.611735E-2,2.15E1,-5.893096E-2,6.761386E-2],"split_indices":[0,0,9,0,0,0,0],"split_type":[0,0,0,0,0,0,0],"sum_hessian":[6.1602216E0,1.4358011E0,4.7244205E0,1.6789837E0,3.0454369E0,1.3795244E0,1.6659125E0],"tree_param":{"num_deleted":"0","num_feature":"11","num_nodes":"7","size_leaf_vector":"1"}},{"base_weights":[6.083122E-2,-8.4954E-2,5.0386524E-1,9.6741565E-2,-5.2200504E-2],"categories":[],"categories_nodes":[],"categories_segments":[],"categories_sizes":[],"default_left":[0,0,0,0,0],"id":20,"left_children":[1,-1,3,-1,-1],"loss_changes":[3.5427775E0,0E0,3.2737646E0,0E0,0E0],"parents":[2147483647,0,0,2,2],"right_children":[2,-1,4,-1,-1],"split_conditions":[0E0,-8.4954E-2,2E1,9.6741565E-2,-5.2200504E-2],"split_indices":[0,0,4,0,0],"split_type":[0,0,0,0,0],"sum_hessian":[6.7226076E0,1.9002718E0,4.8223357E0,3.360733E0,1.4616024E0],"tree_param":{"num_deleted":"0","num_feature":"11","num_nodes":"5","size_leaf_vector":"1"}},{"base_weights":[-8.859611E-2,-5.005781E-1,4.625868E-1,-8.7051034E-2,-8.236777E-2,4.5714667E-3,6.369831E-2,-2.2666762E-2,9.649563E-3],"categories":[],"categories_nodes":[],"categories_segments":[],"categories_sizes":[],"default_left":[0,0,0,0,0,0,0,0,0],"id":21,"left_children":[1,3,5,7,-1,-1,-1,-1,-1],"loss_changes":[1.7869372E0,5.161855E-1,2.2166461E-1,9.99838E-2,0E0,0E0,0E0,0E0,0E0],"parents":[2147483647,0,0,1,1,2,2,3,3],"right_children":[2,4,6,8,-1,-1,-1,-1,-1],"split_conditions":[3.3E1,1.14E1,2.4E0,4E0,-8.236777E-2,4.5714667E-3,6.369831E-2,-2.2666762E-2,9.649563E-3],"split_indices":[1,2,2,2,0,0,0,0,0],"split_type":[0,0,0,0,0,0,0,0,0],"sum_hessian":[5.8495417E0,3.4000118E0,2.44953E0,2.048111E0,1.3519009E0,1.0947646E0,1.3547652E0,1.0298293E0,1.0182817E0],"tree_param":{"num_deleted":"0","num_feature":"11","num_nodes":"9","size_leaf_vector":"1"}},{"base_weights":[6.280309E-2,-7.029762E-2,3.480024E-1,-6.0333855E-2,7.470036E-2,3.5249304E-2,-3.9655138E-2],"categories":[],"categories_nodes":[],"categories_segments":[],"categories_sizes":[],"default_left":[0,0,0,0,0,0,0],"id":22,"left_children":[1,-1,3,5,-1,-1,-1],"loss_changes":[1.8074096E0,0E0,1.0035126E0,6.7174387E-1,0E0,0E0,0E0],"parents":[2147483647,0,0,2,2,3,3],"right_children":[2,-1,4,6,-1,-1,-1],"split_conditions":[-2E-1,-7.029762E-2,4.31E1,7.8E0,7.470036E-2,3.5249304E-2,-3.9655138E-2],"split_indices":[0,0,8,0,0,0,0],"split_type":[0,0,0,0,0,0,0],"sum_hessian":[6.15556E0,1.2728943E0,4.882666E0,2.832591E0,2.0500748E0,1.2497139E0,1.5828773E0],"tree_param":{"num_deleted":"0","num_feature":"11","num_nodes":"7","size_leaf_vector":"1"}},{"base_weights":[-6.263859E-2,-4.4143817E-1,6.872674E-2,-7.64853E-2,-1.04946144E-1,3.393782E-2,-4.7076438E-2],"categories":[],"categories_nodes":[],"categories_segments":[],"categories_sizes":[],"default_left":[0,0,0,0,0,0,0],"id":23,"left_children":[1,3,-1,-1,5,-1,-1],"loss_changes":[2.3246548E0,5.004759E-1,0E0,0E0,7.7326035E-1,0E0,0E0],"parents":[2147483647,0,0,1,1,4,4],"right_children":[2,4,-1,-1,6,-1,-1],"split_conditions":[2.15E1,0E0,6.872674E-2,-7.64853E-2,7.8E0,3.393782E-2,-4.7076438E-2],"split_indices":[0,0,0,0,0,0,0],"split_type":[0,0,0,0,0,0,0],"sum_hessian":[6.115538E0,4.3364244E0,1.7791138E0,1.562056E0,2.7743685E0,1.2853968E0,1.4889717E0],"tree_param":{"num_deleted":"0","num_feature":"11","num_nodes":"7","size_leaf_vector":"1"}},{"base_weights":[-1.3313897E-1,-6.125929E-2,3.3081526E-1,7.667746E-2,-4.2818286E-2],"categories":[],"categories_nodes":[],"categories_segments":[],"categories_sizes":[],"default_left":[0,0,0,0,0],"id":24,"left_children":[1,-1,3,-1,-1],"loss_changes":[1.6333693E0,0E0,1.6247766E0,0E0,0E0],"parents":[2147483647,0,0,2,2],"right_children":[2,-1,4,-1,-1],"split_conditions":[5.542857E0,-6.125929E-2,1.4E1,7.667746E-2,-4.2818286E-2],"split_indices":[9,0,4,0,0],"split_type":[0,0,0,0,0],"sum_hessian":[5.4317756E0,2.5137122E0,2.9180632E0,1.8469512E0,1.071112E0],"tree_param":{"num_deleted":"0","num_feature":"11","num_nodes":"5","size_leaf_vector":"1"}},{"base_weights":[-1.2815677E-1,-6.505623E-2,1.324958E-1,4.9859935E-1,-5.716271E-2,7.7972494E-2,-8.957666E-3],"categories":[],"categories_nodes":[],"categories_segments":[],"categories_sizes":[],"default_left":[0,0,0,0,0,0,0],"id":25,"left_children":[1,-1,3,5,-1,-1,-1],"loss_changes":[9.9785745E-1,0E0,1.6505861E0,7.3445493E-1,0E0,0E0,0E0],"parents":[2147483647,0,0,2,2,3,3],"right_children":[2,-1,4,6,-1,-1,-1],"split_conditions":[2.2428572E0,-6.505623E-2,2E1,1.6E1,-5.716271E-2,7.7972494E-2,-8.957666E-3],"split_indices":[9,0,4,2,0,0,0],"split_type":[0,0,0,0,0,0,0],"sum_hessian":[5.6951976E0,1.3977994E0,4.297398E0,3.0193796E0,1.2780186E0,1.822587E0,1.1967926E0],"tree_param":{"num_deleted":"0","num_feature":"11","num_nodes":"7","size_leaf_vector":"1"}},{"base_weights":[4.226994E-2,-6.339792E-2,3.002143E-1,-3.634512E-2,5.8325744E-1,8.3121754E-2,-4.302091E-3],"categories":[],"categories_nodes":[],"categories_segments":[],"categories_sizes":[],"default_left":[0,0,0,0,0,0,0],"id":26,"left_children":[1,-1,3,-1,5,-1,-1],"loss_changes":[1.3152598E0,0E0,1.2163947E0,0E0,6.7746866E-1,0E0,0E0],"parents":[2147483647,0,0,2,2,4,4],"right_children":[2,-1,4,-1,6,-1,-1],"split_conditions":[0E0,-6.339792E-2,1.4E0,-3.634512E-2,1.19E1,8.3121754E-2,-4.302091E-3],"split_indices":[0,0,2,0,2,0,0],"split_type":[0,0,0,0,0,0,0],"sum_hessian":[5.449007E0,1.1020262E0,4.346981E0,1.2147086E0,3.1322722E0,2.0094461E0,1.1228262E0],"tree_param":{"num_deleted":"0","num_feature":"11","num_nodes":"7","size_leaf_vector":"1"}},{"base_weights":[1.053235E-1,-6.515034E-2,4.0577814E-1,6.849622E-2,-2.500382E-2],"categories":[],"categories_nodes":[],"categories_segments":[],"categories_sizes":[],"default_left":[0,0,0,0,0],"id":27,"left_children":[1,-1,3,-1,-1],"loss_changes":[1.7116933E0,0E0,1.11829E0,0E0,0E0],"parents":[2147483647,0,0,2,2],"right_children":[2,-1,4,-1,-1],"split_conditions":[0E0,-6.515034E-2,2E1,6.849622E-2,-2.500382E-2],"split_indices":[0,0,4,0,0],"split_type":[0,0,0,0,0],"sum_hessian":[5.3648963E0,1.192548E0,4.172348E0,2.8953445E0,1.2770035E0],"tree_param":{"num_deleted":"0","num_feature":"11","num_nodes":"5","size_leaf_vector":"1"}},{"base_weights":[-1.5993902E-1,-5.05987E-1,4.2112045E-2,-7.1412615E-2,-1.23750875E-2],"categories":[],"categories_nodes":[],"categories_segments":[],"categories_sizes":[],"default_left":[0,0,0,0,0],"id":28,"left_children":[1,3,-1,-1,-1],"loss_changes":[1.3318734E0,2.2520363E-1,0E0,0E0,0E0],"parents":[2147483647,0,0,1,1],"right_children":[2,4,-1,-1,-1],"split_conditions":[4.31E1,2.1E1,4.2112045E-2,-7.1412615E-2,-1.23750875E-2],"split_indices":[8,8,0,0,0],"split_type":[0,0,0,0,0],"sum_hessian":[4.5640683E0,2.9414797E0,1.6225888E0,1.3422816E0,1.5991982E0],"tree_param":{"num_deleted":"0","num_feature":"11","num_nodes":"5","size_leaf_vector":"1"}},{"base_weights":[6.278235E-2,-1.7385067E-1,4.2492446E-2,9.125433E-3,-4.2810194E-2],"categories":[],"categories_nodes":[],"categories_segments":[],"categories_sizes":[],"default_left":[0,0,0,0,0],"id":29,"left_children":[1,3,-1,-1,-1],"loss_changes":[5.896402E-1,3.3225453E-1,0E0,0E0,0E0],"parents":[2147483647,0,0,1,1],"right_children":[2,4,-1,-1,-1],"split_conditions":[1.2057143E1,2.74E1,4.2492446E-2,9.125433E-3,-4.2810194E-2],"split_indices":[9,8,0,0,0],"split_type":[0,0,0,0,0],"sum_hessian":[5.018649E0,3.3497643E0,1.6688848E0,1.9537239E0,1.3960404E0],"tree_param":{"num_deleted":"0","num_feature":"11","num_nodes":"5","size_leaf_vector":"1"}},{"base_weights":[5.809362E-2,-6.416763E-2,4.09572E-1,5.7662125E-3,6.3828655E-2],"categories":[],"categories_nodes":[],"categories_segments":[],"categories_sizes":[],"default_left":[0,0,0,0,0],"id":30,"left_children":[1,-1,3,-1,-1],"loss_changes":[1.6008134E0,0E0,3.0378288E-1,0E0,0E0],"parents":[2147483647,0,0,2,2],"right_children":[2,-1,4,-1,-1],"split_conditions":[0E0,-6.416763E-2,1.2E1,5.7662125E-3,6.3828655E-2],"split_indices":[0,0,0,0,0],"split_type":[0,0,0,0,0],"sum_hessian":[4.4400444E0,1.2084507E0,3.2315938E0,1.7661833E0,1.4654107E0],"tree_param":{"num_deleted":"0","num_feature":"11","num_nodes":"5","size_leaf_vector":"1"}},{"base_weights":[-1.1452963E-1,-4.7413272E-1,6.2296636E-2,-2.0789345E-1,-7.0848756E-2,-5.4376002E-2,3.0915663E-2],"categories":[],"categories_nodes":[],"categories_segments":[],"categories_sizes":[],"default_left":[0,0,0,0,0,0,0],"id":31,"left_children":[1,3,-1,5,-1,-1,-1],"loss_changes":[1.9015656E0,1.4216399E-1,0E0,7.9104257E-1,0E0,0E0,0E0],"parents":[2147483647,0,0,1,1,3,3],"right_children":[2,4,-1,6,-1,-1,-1],"split_conditions":[2.15E1,4E0,6.2296636E-2,6E0,-7.0848756E-2,-5.4376002E-2,3.0915663E-2],"split_indices":[0,7,0,0,0,0,0],"split_type":[0,0,0,0,0,0,0],"sum_hessian":[5.0564156E0,3.6390965E0,1.4173189E0,2.5871022E0,1.0519943E0,1.5370219E0,1.0500803E0],"tree_param":{"num_deleted":"0","num_feature":"11","num_nodes":"7","size_leaf_vector":"1"}},{"base_weights":[3.0122608E-2,-2.420065E-1,5.801792E-2,-6.426128E-2,1.17406465E-1,4.623386E-2,-2.3943398E-2],"categories":[],"categories_nodes":[],"categories_segments":[],"categories_sizes":[],"default_left":[0,0,0,0,0,0,0],"id":32,"left_children":[1,3,-1,-1,5,-1,-1],"loss_changes":[1.0084504E0,7.3565835E-1,0E0,0E0,5.122613E-1,0E0,0E0],"parents":[2147483647,0,0,1,1,4,4],"right_children":[2,4,-1,-1,6,-1,-1],"split_conditions":[2.15E1,3E0,5.801792E-2,-6.426128E-2,2.02E1,4.623386E-2,-2.3943398E-2],"split_indices":[0,2,0,0,8,0,0],"split_type":[0,0,0,0,0,0,0],"sum_hessian":[4.799078E0,3.5853393E0,1.2137387E0,1.3228842E0,2.2624552E0,1.0000924E0,1.2623627E0],"tree_param":{"num_deleted":"0","num_feature":"11","num_nodes":"7","size_leaf_vector":"1"}},{"base_weights":[8.272343E-2,-6.279855E-2,4.0013826E-1,8.322965E-2,-1.9351186E-2],"categories":[],"categories_nodes":[],"categories_segments":[],"categories_sizes":[],"default_left":[0,0,0,0,0],"id":33,"left_children":[1,-1,3,-1,-1],"loss_changes":[1.5783099E0,0E0,1.360995E0,0E0,0E0],"parents":[2147483647,0,0,2,2],"right_children":[2,-1,4,-1,-1],"split_conditions":[0E0,-6.279855E-2,4E0,8.322965E-2,-1.9351186E-2],"split_indices":[0,0,7,0,0],"split_type":[0,0,0,0,0],"sum_hessian":[4.882493E0,1.2053072E0,3.6771855E0,1.895398E0,1.7817875E0],"tree_param":{"num_deleted":"0","num_feature":"11","num_nodes":"5","size_leaf_vector":"1"}},{"base_weights":[-3.9474163E-3,-2.6510808E-1,5.4392047E-2,5.2518904E-4,-3.741911E-2],"categories":[],"categories_nodes":[],"categories_segments":[],"categories_sizes":[],"default_left":[0,0,0,0,0],"id":34,"left_children":[1,3,-1,-1,-1],"loss_changes":[9.137729E-1,1.292114E-1,0E0,0E0,0E0],"parents":[2147483647,0,0,1,1],"right_children":[2,4,-1,-1,-1],"split_conditions":[2.15E1,5.8E0,5.4392047E-2,5.2518904E-4,-3.741911E-2],"split_indices":[0,0,0,0,0],"split_type":[0,0,0,0,0],"sum_hessian":[4.3785787E0,3.3146448E0,1.0639337E0,1.2265418E0,2.088103E0],"tree_param":{"num_deleted":"0","num_feature":"11","num_nodes":"5","size_leaf_vector":"1"}},{"base_weights":[7.319509E-2,-3.23442E-1,5.1730633E-2,1.43703045E-2,-6.1834376E-2],"categories":[],"categories_nodes":[],"categories_segments":[],"categories_sizes":[],"default_left":[0,0,0,0,0],"id":35,"left_children":[1,3,-1,-1,-1],"loss_changes":[1.0839603E0,5.522992E-1,0E0,0E0,0E0],"parents":[2147483647,0,0,1,1],"right_children":[2,4,-1,-1,-1],"split_conditions":[9.6E0,1.5806939E1,5.1730633E-2,1.43703045E-2,-6.1834376E-2],"split_indices":[0,10,0,0,0],"split_type":[0,0,0,0,0],"sum_hessian":[4.2037272E0,2.3640747E0,1.8396527E0,1.113276E0,1.2507986E0],"tree_param":{"num_deleted":"0","num_feature":"11","num_nodes":"5","size_leaf_vector":"1"}},{"base_weights":[-7.429058E-2,-6.5126486E-2,3.7450606E-1,5.168263E-2,5.475987E-3],"categories":[],"categories_nodes":[],"categories_segments":[],"categories_sizes":[],"default_left":[0,0,0,0,0],"id":36,"left_children":[1,-1,3,-1,-1],"loss_changes":[1.4353741E0,0E0,1.1836645E-1,0E0,0E0],"parents":[2147483647,0,0,2,2],"right_children":[2,-1,4,-1,-1],"split_conditions":[1.2E1,-6.5126486E-2,7E0,5.168263E-2,5.475987E-3],"split_indices":[1,0,4,0,0],"split_type":[0,0,0,0,0],"sum_hessian":[3.601269E0,1.3782504E0,2.2230186E0,1.1117918E0,1.1112268E0],"tree_param":{"num_deleted":"0","num_feature":"11","num_nodes":"5","size_leaf_vector":"1"}},{"base_weights":[7.6361857E-3,-4.9392067E-2,2.617022E-1,-2.1859752E-2,4.6645436E-1,7.265152E-2,9.580577E-4],"categories":[],"categories_nodes":[],"categories_segments":[],"categories_sizes":[],"default_left":[0,0,0,0,0,0,0],"id":37,"left_children":[1,-1,3,-1,5,-1,-1],"loss_changes":[8.6527115E-1,0E0,5.432762E-1,0E0,4.047737E-1,0E0,0E0],"parents":[2147483647,0,0,2,2,4,4],"right_children":[2,-1,4,-1,6,-1,-1],"split_conditions":[1.4E0,-4.9392067E-2,4.4E0,-2.1859752E-2,1.04E1,7.265152E-2,9.580577E-4],"split_indices":[2,0,0,0,0,0,0],"split_type":[0,0,0,0,0,0,0],"sum_hessian":[4.775872E0,1.2883837E0,3.4874885E0,1.0221494E0,2.4653392E0,1.1949588E0,1.2703803E0],"tree_param":{"num_deleted":"0","num_feature":"11","num_nodes":"7","size_leaf_vector":"1"}},{"base_weights":[-1.774067E-1,-4.9220324E-2,3.2068662E-2],"categories":[],"categories_nodes":[],"categories_segments":[],"categories_sizes":[],"default_left":[0,0,0],"id":38,"left_children":[1,-1,-1],"loss_changes":[9.5745057E-1,0E0,0E0],"parents":[2147483647,0,0],"right_children":[2,-1,-1],"split_conditions":[2.2033347E2,-4.9220324E-2,3.2068662E-2],"split_indices":[10,0,0],"split_type":[0,0,0],"sum_hessian":[4.0996013E0,2.5192516E0,1.5803496E0],"tree_param":{"num_deleted":"0","num_feature":"11","num_nodes":"3","size_leaf_vector":"1"}},{"base_weights":[-5.4410644E-2,-5.2842613E-2,1.9145225E-1,-9.745556E-3,3.312875E-2],"categories":[],"categories_nodes":[],"categories_segments":[],"categories_sizes":[],"default_left":[0,0,0,0,0],"id":39,"left_children":[1,-1,3,-1,-1],"loss_changes":[6.9629866E-1,0E0,1.977836E-1,0E0,0E0],"parents":[2147483647,0,0,2,2],"right_children":[2,-1,4,-1,-1],"split_conditions":[2E0,-5.2842613E-2,3E0,-9.745556E-3,3.312875E-2],"split_indices":[2,0,7,0,0],"split_type":[0,0,0,0,0],"sum_hessian":[4.1065383E0,1.0100069E0,3.0965312E0,1.1087852E0,1.987746E0],"tree_param":{"num_deleted":"0","num_feature":"11","num_nodes":"5","size_leaf_vector":"1"}},{"base_weights":[-2.053077E-1,-4.6673656E-1,2.9515196E-2,-7.8007127E-3,-5.777405E-2],"categories":[],"categories_nodes":[],"categories_segments":[],"categories_sizes":[],"default_left":[0,0,0,0,0],"id":40,"left_children":[1,3,-1,-1,-1],"loss_changes":[8.473507E-1,1.2537539E-1,0E0,0E0,0E0],"parents":[2147483647,0,0,1,1],"right_children":[2,4,-1,-1,-1],"split_conditions":[2.2033347E2,1.9285715E0,2.9515196E-2,-7.8007127E-3,-5.777405E-2],"split_indices":[10,9,0,0,0],"split_type":[0,0,0,0,0],"sum_hessian":[4.423586E0,2.9499714E0,1.4736143E0,1.0334902E0,1.9164811E0],"tree_param":{"num_deleted":"0","num_feature":"11","num_nodes":"5","size_leaf_vector":"1"}},{"base_weights":[-3.4607764E-2,-2.840917E-1,5.3031284E-2,4.1359644E-3,-5.6386825E-2],"categories":[],"categories_nodes":[],"categories_segments":[],"categories_sizes":[],"default_left":[0,0,0,0,0],"id":41,"left_children":[1,3,-1,-1,-1],"loss_changes":[9.159288E-1,4.2556182E-1,0E0,0E0,0E0],"parents":[2147483647,0,0,1,1],"right_children":[2,4,-1,-1,-1],"split_conditions":[2.15E1,7.8E0,5.3031284E-2,4.1359644E-3,-5.6386825E-2],"split_indices":[0,0,0,0,0],"split_type":[0,0,0,0,0],"sum_hessian":[4.4298196E0,3.41762E0,1.0121998E0,1.9737799E0,1.4438401E0],"tree_param":{"num_deleted":"0","num_feature":"11","num_nodes":"5","size_leaf_vector":"1"}},{"base_weights":[1.0743082E-1,-2.7067095E-2,4.8034288E-2],"categories":[],"categories_nodes":[],"categories_segments":[],"categories_sizes":[],"default_left":[0,0,0],"id":42,"left_children":[1,-1,-1],"loss_changes":[8.032002E-1,0E0,0E0],"parents":[2147483647,0,0],"right_children":[2,-1,-1],"split_conditions":[9.6E0,-2.7067095E-2,4.8034288E-2],"split_indices":[0,0,0],"split_type":[0,0,0],"sum_hessian":[3.7744076E0,2.0103002E0,1.7641075E0],"tree_param":{"num_deleted":"0","num_feature":"11","num_nodes":"3","size_leaf_vector":"1"}},{"base_weights":[-1.7959714E-1,-4.312129E-1,2.8161203E-2,8.785497E-3,-6.982577E-2],"categories":[],"categories_nodes":[],"categories_segments":[],"categories_sizes":[],"default_left":[0,0,0,0,0],"id":43,"left_children":[1,3,-1,-1,-1],"loss_changes":[7.266372E-1,5.838296E-1,0E0,0E0,0E0],"parents":[2147483647,0,0,1,1],"right_children":[2,4,-1,-1,-1],"split_conditions":[2.2033347E2,6.4E0,2.8161203E-2,8.785497E-3,-6.982577E-2],"split_indices":[10,1,0,0,0],"split_type":[0,0,0,0,0],"sum_hessian":[4.215127E0,2.7693357E0,1.4457912E0,1.1686958E0,1.60064E0],"tree_param":{"num_deleted":"0","num_feature":"11","num_nodes":"5","size_leaf_vector":"1"}},{"base_weights":[-8.6088814E-2,-3.6385324E-2,2.0582628E-2],"categories":[],"categories_nodes":[],"categories_segments":[],"categories_sizes":[],"default_left":[0,0,0],"id":44,"left_children":[1,-1,-1],"loss_changes":[4.6230325E-1,0E0,0E0],"parents":[2147483647,0,0],"right_children":[2,-1,-1],"split_conditions":[5.542857E0,-3.6385324E-2,2.0582628E-2],"split_indices":[9,0,0],"split_type":[0,0,0],"sum_hessian":[3.77794E0,1.8096131E0,1.9683268E0],"tree_param":{"num_deleted":"0","num_feature":"11","num_nodes":"3","size_leaf_vector":"1"}},{"base_weights":[2.939026E-2,-4.8102744E-2,3.4542465E-1,-5.565431E-3,6.313735E-2],"categories":[],"categories_nodes":[],"categories_segments":[],"categories_sizes":[],"default_left":[0,0,0,0,0],"id":45,"left_children":[1,-1,3,-1,-1],"loss_changes":[9.520267E-1,0E0,4.4696853E-1,0E0,0E0],"parents":[2147483647,0,0,2,2],"right_children":[2,-1,4,-1,-1],"split_conditions":[2.2E0,-4.8102744E-2,5.542857E0,-5.565431E-3,6.313735E-2],"split_indices":[2,0,9,0,0],"split_type":[0,0,0,0,0],"sum_hessian":[3.8718007E0,1.2809322E0,2.5908685E0,1.4135535E0,1.177315E0],"tree_param":{"num_deleted":"0","num_feature":"11","num_nodes":"5","size_leaf_vector":"1"}},{"base_weights":[-4.432373E-2,1.7966045E-1,-4.7089055E-2,-1.22124135E-1,5.8520086E-2,1.9954806E-2,-4.185313E-2],"categories":[],"categories_nodes":[],"categories_segments":[],"categories_sizes":[],"default_left":[0,0,0,0,0,0,0],"id":46,"left_children":[1,3,-1,5,-1,-1,-1],"loss_changes":[6.0880405E-1,6.003376E-1,0E0,3.9863122E-1,0E0,0E0,0E0],"parents":[2147483647,0,0,1,1,3,3],"right_children":[2,4,-1,6,-1,-1,-1],"split_conditions":[2E1,5.542857E0,-4.7089055E-2,1.5806939E1,5.8520086E-2,1.9954806E-2,-4.185313E-2],"split_indices":[4,9,0,10,0,0,0],"split_type":[0,0,0,0,0,0,0],"sum_hessian":[4.4865026E0,3.3213377E0,1.1651651E0,2.3049557E0,1.0163819E0,1.2620782E0,1.0428776E0],"tree_param":{"num_deleted":"0","num_feature":"11","num_nodes":"7","size_leaf_vector":"1"}},{"base_weights":[7.458557E-2,3.400035E-1,-4.4982083E-2,4.726405E-2,2.6555776E-3],"categories":[],"categories_nodes":[],"categories_segments":[],"categories_sizes":[],"default_left":[0,0,0,0,0],"id":47,"left_children":[1,3,-1,-1,-1],"loss_changes":[8.3630455E-1,1.4665186E-1,0E0,0E0,0E0],"parents":[2147483647,0,0,1,1],"right_children":[2,4,-1,-1,-1],"split_conditions":[1.6E1,1.1171429E1,-4.4982083E-2,4.726405E-2,2.6555776E-3],"split_indices":[2,9,0,0,0],"split_type":[0,0,0,0,0],"sum_hessian":[3.9096878E0,2.829323E0,1.0803646E0,1.6311969E0,1.1981262E0],"tree_param":{"num_deleted":"0","num_feature":"11","num_nodes":"5","size_leaf_vector":"1"}},{"base_weights":[5.154613E-2,3.2789236E-1,-4.1297305E-2,3.4009446E-3,5.1238783E-2],"categories":[],"categories_nodes":[],"categories_segments":[],"categories_sizes":[],"default_left":[0,0,0,0,0],"id":48,"left_children":[1,3,-1,-1,-1],"loss_changes":[7.4356323E-1,1.7385426E-1,0E0,0E0,0E0],"parents":[2147483647,0,0,1,1],"right_children":[2,4,-1,-1,-1],"split_conditions":[2E1,1.2E1,-4.1297305E-2,3.4009446E-3,5.1238783E-2],"split_indices":[4,1,0,0,0],"split_type":[0,0,0,0,0],"sum_hessian":[3.737567E0,2.5278523E0,1.2097147E0,1.4316746E0,1.0961778E0],"tree_param":{"num_deleted":"0","num_feature":"11","num_nodes":"5","size_leaf_vector":"1"}},{"base_weights":[5.5804603E-2,2.745519E-1,-3.8036577E-2,-9.812226E-3,5.922698E-2],"categories":[],"categories_nodes":[],"categories_segments":[],"categories_sizes":[],"default_left":[0,0,0,0,0],"id":49,"left_children":[1,3,-1,-1,-1],"loss_changes":[5.639406E-1,5.06667E-1,0E0,0E0,0E0],"parents":[2147483647,0,0,1,1],"right_children":[2,4,-1,-1,-1],"split_conditions":[1.6E1,3E0,-3.8036577E-2,-9.812226E-3,5.922698E-2],"split_indices":[2,2,0,0,0],"split_type":[0,0,0,0,0],"sum_hessian":[3.8161123E0,2.7882795E0,1.0278327E0,1.6012378E0,1.1870416E0],"tree_param":{"num_deleted":"0","num_feature":"11","num_nodes":"5","size_leaf_vector":"1"}},{"base_weights":[5.8590874E-2,-3.6810454E-2,2.8649312E-1,5.61773E-2,-1.7232668E-2],"categories":[],"categories_nodes":[],"categories_segments":[],"categories_sizes":[],"default_left":[0,0,0,0,0],"id":50,"left_children":[1,-1,3,-1,-1],"loss_changes":[6.187789E-1,0E0,6.024254E-1,0E0,0E0],"parents":[2147483647,0,0,2,2],"right_children":[2,-1,4,-1,-1],"split_conditions":[1.4E0,-3.6810454E-2,1.6E1,5.61773E-2,-1.7232668E-2],"split_indices":[2,0,2,0,0],"split_type":[0,0,0,0,0],"sum_hessian":[4.278629E0,1.2754505E0,3.0031784E0,1.7367729E0,1.2664055E0],"tree_param":{"num_deleted":"0","num_feature":"11","num_nodes":"5","size_leaf_vector":"1"}},{"base_weights":[-4.9594153E-2,-2.5257966E-1,3.2619547E-2,-5.2289814E-2,5.495628E-3],"categories":[],"categories_nodes":[],"categories_segments":[],"categories_sizes":[],"default_left":[0,0,0,0,0],"id":51,"left_children":[1,3,-1,-1,-1],"loss_changes":[4.876521E-1,3.6235893E-1,0E0,0E0,0E0],"parents":[2147483647,0,0,1,1],"right_children":[2,4,-1,-1,-1],"split_conditions":[1.2E1,3E0,3.2619547E-2,-5.2289814E-2,5.495628E-3],"split_indices":[0,2,0,0,0],"split_type":[0,0,0,0,0],"sum_hessian":[4.3128295E0,3.013133E0,1.2996962E0,1.2309059E0,1.7822272E0],"tree_param":{"num_deleted":"0","num_feature":"11","num_nodes":"5","size_leaf_vector":"1"}},{"base_weights":[1.4437407E-2,2.83391E-1,-4.6261925E-2,-2.0073252E-2,6.7019716E-2],"categories":[],"categories_nodes":[],"categories_segments":[],"categories_sizes":[],"default_left":[0,0,0,0,0],"id":52,"left_children":[1,3,-1,-1,-1],"loss_changes":[7.4131143E-1,8.2017237E-1,0E0,0E0,0E0],"parents":[2147483647,0,0,1,1],"right_children":[2,4,-1,-1,-1],"split_conditions":[2E1,6E0,-4.6261925E-2,-2.0073252E-2,6.7019716E-2],"split_indices":[4,0,0,0,0],"split_type":[0,0,0,0,0],"sum_hessian":[3.7558868E0,2.6614065E0,1.0944803E0,1.3956603E0,1.2657461E0],"tree_param":{"num_deleted":"0","num_feature":"11","num_nodes":"5","size_leaf_vector":"1"}},{"base_weights":[-2.3476587E-1,-4.4527227E-1,2.2519251E-2,-1.7949578E-3,-6.257825E-2],"categories":[],"categories_nodes":[],"categories_segments":[],"categories_sizes":[],"default_left":[0,0,0,0,0],"id":53,"left_children":[1,3,-1,-1,-1],"loss_changes":[5.2109474E-1,2.446692E-1,0E0,0E0,0E0],"parents":[2147483647,0,0,1,1],"right_children":[2,4,-1,-1,-1],"split_conditions":[1.2E1,5.2E0,2.2519251E-2,-1.7949578E-3,-6.257825E-2],"split_indices":[0,0,0,0,0],"split_type":[0,0,0,0,0],"sum_hessian":[3.3462567E0,2.317534E0,1.0287226E0,1.01475E0,1.302784E0],"tree_param":{"num_deleted":"0","num_feature":"11","num_nodes":"5","size_leaf_vector":"1"}},{"base_weights":[1.0137077E-1,3.3724472E-1,-3.6720157E-2,4.9902268E-2,-4.5303027E-3],"categories":[],"categories_nodes":[],"categories_segments":[],"categories_sizes":[],"default_left":[0,0,0,0,0],"id":54,"left_children":[1,3,-1,-1,-1],"loss_changes":[6.795125E-1,2.6183268E-1,0E0,0E0,0E0],"parents":[2147483647,0,0,1,1],"right_children":[2,4,-1,-1,-1],"split_conditions":[2E1,1.13E1,-3.6720157E-2,4.9902268E-2,-4.5303027E-3],"split_indices":[4,2,0,0,0],"split_type":[0,0,0,0,0],"sum_hessian":[4.0276465E0,2.8654723E0,1.1621742E0,1.799851E0,1.0656215E0],"tree_param":{"num_deleted":"0","num_feature":"11","num_nodes":"5","size_leaf_vector":"1"}},{"base_weights":[2.0962514E-3,-3.5170227E-2,2.1179765E-1,6.018224E-2,-3.4333095E-2],"categories":[],"categories_nodes":[],"categories_segments":[],"categories_sizes":[],"default_left":[0,0,0,0,0],"id":55,"left_children":[1,-1,3,-1,-1],"loss_changes":[3.9963317E-1,0E0,9.375109E-1,0E0,0E0],"parents":[2147483647,0,0,2,2],"right_children":[2,-1,4,-1,-1],"split_conditions":[1.4E0,-3.5170227E-2,1.6E1,6.018224E-2,-3.4333095E-2],"split_indices":[2,0,2,0,0],"split_type":[0,0,0,0,0],"sum_hessian":[3.3824563E0,1.0067525E0,2.3757038E0,1.3459482E0,1.0297557E0],"tree_param":{"num_deleted":"0","num_feature":"11","num_nodes":"5","size_leaf_vector":"1"}},{"base_weights":[-8.76532E-2,-3.1049494E-2,2.5213122E-2],"categories":[],"categories_nodes":[],"categories_segments":[],"categories_sizes":[],"default_left":[0,0,0],"id":56,"left_children":[1,-1,-1],"loss_changes":[3.8807163E-1,0E0,0E0],"parents":[2147483647,0,0],"right_children":[2,-1,-1],"split_conditions":[9E0,-3.1049494E-2,2.5213122E-2],"split_indices":[2,0,0],"split_type":[0,0,0],"sum_hessian":[3.091307E0,1.9189783E0,1.1723285E0],"tree_param":{"num_deleted":"0","num_feature":"11","num_nodes":"3","size_leaf_vector":"1"}},{"base_weights":[7.4507736E-2,2.512852E-1,-2.7629727E-2,-1.7441599E-2,4.9701203E-2],"categories":[],"categories_nodes":[],"categories_segments":[],"categories_sizes":[],"default_left":[0,0,0,0,0],"id":57,"left_children":[1,3,-1,-1,-1],"loss_changes":[3.627169E-1,4.7042257E-1,0E0,0E0,0E0],"parents":[2147483647,0,0,1,1],"right_children":[2,4,-1,-1,-1],"split_conditions":[1.4E1,4.5E0,-2.7629727E-2,-1.7441599E-2,4.9701203E-2],"split_indices":[4,0,0,0,0],"split_type":[0,0,0,0,0],"sum_hessian":[3.7293444E0,2.6683838E0,1.0609605E0,1.0827734E0,1.5856104E0],"tree_param":{"num_deleted":"0","num_feature":"11","num_nodes":"5","size_leaf_vector":"1"}},{"base_weights":[-5.0491977E-2,-2.5940952E-1,1.9607214E-2,2.3140082E-2,-5.971505E-2],"categories":[],"categories_nodes":[],"categories_segments":[],"categories_sizes":[],"default_left":[0,0,0,0,0],"id":58,"left_children":[1,3,-1,-1,-1],"loss_changes":[3.1091404E-1,6.625519E-1,0E0,0E0,0E0],"parents":[2147483647,0,0,1,1],"right_children":[2,4,-1,-1,-1],"split_conditions":[2.1E1,6.4E0,1.9607214E-2,2.3140082E-2,-5.971505E-2],"split_indices":[1,1,0,0,0],"split_type":[0,0,0,0,0],"sum_hessian":[4.048402E0,2.1633039E0,1.885098E0,1.0101687E0,1.1531352E0],"tree_param":{"num_deleted":"0","num_feature":"11","num_nodes":"5","size_leaf_vector":"1"}},{"base_weights":[-1.5559693E-1,-3.802047E-2,2.4802437E-2],"categories":[],"categories_nodes":[],"categories_segments":[],"categories_sizes":[],"default_left":[0,0,0],"id":59,"left_children":[1,-1,-1],"loss_changes":[4.933361E-1,0E0,0E0],"parents":[2147483647,0,0],"right_children":[2,-1,-1],"split_conditions":[2.2033347E2,-3.802047E-2,2.4802437E-2],"split_indices":[10,0,0],"split_type":[0,0,0],"sum_hessian":[3.401628E0,2.222734E0,1.1788939E0],"tree_param":{"num_deleted":"0","num_feature":"11","num_nodes":"3","size_leaf_vector":"1"}},{"base_weights":[7.213466E-3,2.7386932E-2,-3.3242337E-2],"categories":[],"categories_nodes":[],"categories_segments":[],"categories_sizes":[],"default_left":[0,0,0],"id":60,"left_children":[1,-1,-1],"loss_changes":[4.9376565E-1,0E0,0E0],"parents":[2147483647,0,0],"right_children":[2,-1,-1],"split_conditions":[6.3E0,2.7386932E-2,-3.3242337E-2],"split_indices":[2,0,0],"split_type":[0,0,0],"sum_hessian":[3.4467509E0,2.0392973E0,1.4074534E0],"tree_param":{"num_deleted":"0","num_feature":"11","num_nodes":"3","size_leaf_vector":"1"}},{"base_weights":[6.3220665E-2,-3.0158896E-2,2.6421705E-1,3.806403E-2,-1.8810912E-3],"categories":[],"categories_nodes":[],"categories_segments":[],"categories_sizes":[],"default_left":[0,0,0,0,0],"id":61,"left_children":[1,-1,3,-1,-1],"loss_changes":[4.3688002E-1,0E0,1.2821877E-1,0E0,0E0],"parents":[2147483647,0,0,2,2],"right_children":[2,-1,4,-1,-1],"split_conditions":[1.4E0,-3.0158896E-2,2.74E1,3.806403E-2,-1.8810912E-3],"split_indices":[2,0,8,0,0],"split_type":[0,0,0,0,0],"sum_hessian":[3.8713682E0,1.1974748E0,2.6738935E0,1.6501999E0,1.0236936E0],"tree_param":{"num_deleted":"0","num_feature":"11","num_nodes":"5","size_leaf_vector":"1"}},{"base_weights":[-7.526136E-2,-2.2889076E-1,2.2817453E-2,-2.2311616E-3,-3.0482566E-2],"categories":[],"categories_nodes":[],"categories_segments":[],"categories_sizes":[],"default_left":[0,0,0,0,0],"id":62,"left_children":[1,3,-1,-1,-1],"loss_changes":[2.7935988E-1,5.1770434E-2,0E0,0E0,0E0],"parents":[2147483647,0,0,1,1],"right_children":[2,4,-1,-1,-1],"split_conditions":[2.2033347E2,1.9733877E1,2.2817453E-2,-2.2311616E-3,-3.0482566E-2],"split_indices":[10,10,0,0,0],"split_type":[0,0,0,0,0],"sum_hessian":[3.8723524E0,2.7338674E0,1.1384852E0,1.0825744E0,1.6512929E0],"tree_param":{"num_deleted":"0","num_feature":"11","num_nodes":"5","size_leaf_vector":"1"}},{"base_weights":[-7.831737E-3,1.7955618E-1,-2.941041E-2,-1.6570304E-2,4.0985476E-2],"categories":[],"categories_nodes":[],"categories_segments":[],"categories_sizes":[],"default_left":[0,0,0,0,0],"id":63,"left_children":[1,3,-1,-1,-1],"loss_changes":[2.9328024E-1,3.3270833E-1,0E0,0E0,0E0],"parents":[2147483647,0,0,1,1],"right_children":[2,4,-1,-1,-1],"split_conditions":[2E1,4.5E0,-2.941041E-2,-1.6570304E-2,4.0985476E-2],"split_indices":[4,0,0,0,0],"split_type":[0,0,0,0,0],"sum_hessian":[3.4827406E0,2.3302114E0,1.1525294E0,1.0446213E0,1.2855899E0],"tree_param":{"num_deleted":"0","num_feature":"11","num_nodes":"5","size_leaf_vector":"1"}},{"base_weights":[-1.048109E-1,-2.928476E-1,2.7678112E-2,-4.420581E-2,-4.3322477E-3],"categories":[],"categories_nodes":[],"categories_segments":[],"categories_sizes":[],"default_left":[0,0,0,0,0],"id":64,"left_children":[1,3,-1,-1,-1],"loss_changes":[4.2080355E-1,1.1703637E-1,0E0,0E0,0E0],"parents":[2147483647,0,0,1,1],"right_children":[2,4,-1,-1,-1],"split_conditions":[1.2E1,3.1E0,2.7678112E-2,-4.420581E-2,-4.3322477E-3],"split_indices":[0,2,0,0,0],"split_type":[0,0,0,0,0],"sum_hessian":[3.7349584E0,2.6578274E0,1.0771312E0,1.1803852E0,1.477442E0],"tree_param":{"num_deleted":"0","num_feature":"11","num_nodes":"5","size_leaf_vector":"1"}},{"base_weights":[-6.1588693E-2,-3.2099742E-2,1.901119E-2],"categories":[],"categories_nodes":[],"categories_segments":[],"categories_sizes":[],"default_left":[0,0,0],"id":65,"left_children":[1,-1,-1],"loss_changes":[3.5828376E-1,0E0,0E0],"parents":[2147483647,0,0],"right_children":[2,-1,-1],"split_conditions":[5.542857E0,-3.2099742E-2,1.901119E-2],"split_indices":[9,0,0],"split_type":[0,0,0],"sum_hessian":[3.5526607E0,1.61396E0,1.9387008E0],"tree_param":{"num_deleted":"0","num_feature":"11","num_nodes":"3","size_leaf_vector":"1"}},{"base_weights":[4.7169454E-2,-2.3810397E-1,4.470118E-2,-2.5957518E-3,-3.36405E-2],"categories":[],"categories_nodes":[],"categories_segments":[],"categories_sizes":[],"default_left":[0,0,0,0,0],"id":66,"left_children":[1,3,-1,-1,-1],"loss_changes":[5.823916E-1,5.5659354E-2,0E0,0E0,0E0],"parents":[2147483647,0,0,1,1],"right_children":[2,4,-1,-1,-1],"split_conditions":[1.2381388E2,1.4582449E1,4.470118E-2,-2.5957518E-3,-3.36405E-2],"split_indices":[10,10,0,0,0],"split_type":[0,0,0,0,0],"sum_hessian":[3.1726985E0,2.087702E0,1.0849965E0,1.0613124E0,1.0263895E0],"tree_param":{"num_deleted":"0","num_feature":"11","num_nodes":"5","size_leaf_vector":"1"}},{"base_weights":[-5.2181352E-2,-2.229079E-1,2.8271187E-2,1.0880281E-2,-3.8256116E-2],"categories":[],"categories_nodes":[],"categories_segments":[],"categories_sizes":[],"default_left":[0,0,0,0,0],"id":67,"left_children":[1,3,-1,-1,-1],"loss_changes":[3.4453577E-1,2.4394473E-1,0E0,0E0,0E0],"parents":[2147483647,0,0,1,1],"right_children":[2,4,-1,-1,-1],"split_conditions":[1.2E1,5.6E0,2.8271187E-2,1.0880281E-2,-3.8256116E-2],"split_indices":[0,1,0,0,0],"split_type":[0,0,0,0,0],"sum_hessian":[3.9237645E0,2.8203554E0,1.103409E0,1.019874E0,1.8004814E0],"tree_param":{"num_deleted":"0","num_feature":"11","num_nodes":"5","size_leaf_vector":"1"}},{"base_weights":[-1.9148448E-2,-3.552057E-2,2.2771361E-1,5.3239323E-2,-1.4624785E-2],"categories":[],"categories_nodes":[],"categories_segments":[],"categories_sizes":[],"default_left":[0,0,0,0,0],"id":68,"left_children":[1,-1,3,-1,-1],"loss_changes":[4.5990738E-1,0E0,4.4739467E-1,0E0,0E0],"parents":[2147483647,0,0,2,2],"right_children":[2,-1,4,-1,-1],"split_conditions":[3E0,-3.552057E-2,1.6E1,5.3239323E-2,-1.4624785E-2],"split_indices":[2,0,2,0,0],"split_type":[0,0,0,0,0],"sum_hessian":[3.568746E0,1.325474E0,2.243272E0,1.0026884E0,1.2405837E0],"tree_param":{"num_deleted":"0","num_feature":"11","num_nodes":"5","size_leaf_vector":"1"}},{"base_weights":[1.8441118E-2,-2.372886E-2,2.2907605E-2],"categories":[],"categories_nodes":[],"categories_segments":[],"categories_sizes":[],"default_left":[0,0,0],"id":69,"left_children":[1,-1,-1],"loss_changes":[2.899294E-1,0E0,0E0],"parents":[2147483647,0,0],"right_children":[2,-1,-1],"split_conditions":[2.02E1,-2.372886E-2,2.2907605E-2],"split_indices":[8,0,0],"split_type":[0,0,0],"sum_hessian":[3.3733325E0,1.4664233E0,1.9069092E0],"tree_param":{"num_deleted":"0","num_feature":"11","num_nodes":"3","size_leaf_vector":"1"}},{"base_weights":[-2.4192606E-1,-4.473745E-2,1.6803507E-2],"categories":[],"categories_nodes":[],"categories_segments":[],"categories_sizes":[],"default_left":[0,0,0],"id":70,"left_children":[1,-1,-1],"loss_changes":[3.9677835E-1,0E0,0E0],"parents":[2147483647,0,0],"right_children":[2,-1,-1],"split_conditions":[2.1E1,-4.473745E-2,1.6803507E-2],"split_indices":[1,0,0],"split_type":[0,0,0],"sum_hessian":[2.8183486E0,1.8166764E0,1.0016723E0],"tree_param":{"num_deleted":"0","num_feature":"11","num_nodes":"3","size_leaf_vector":"1"}},{"base_weights":[8.398446E-2,-3.873051E-2,3.9096434E-2],"categories":[],"categories_nodes":[],"categories_segments":[],"categories_sizes":[],"default_left":[0,0,0],"id":71,"left_children":[1,-1,-1],"loss_changes":[7.1218103E-1,0E0,0E0],"parents":[2147483647,0,0],"right_children":[2,-1,-1],"split_conditions":[2.2428572E0,-3.873051E-2,3.9096434E-2],"split_indices":[9,0,0],"split_type":[0,0,0],"sum_hessian":[2.8759503E0,1.0311772E0,1.8447732E0],"tree_param":{"num_deleted":"0","num_feature":"11","num_nodes":"3","size_leaf_vector":"1"}},{"base_weights":[-7.580605E-2,1.257571E-1,-3.888167E-2,-1.9213352E-2,3.3604585E-2],"categories":[],"categories_nodes":[],"categories_segments":[],"categories_sizes":[],"default_left":[0,0,0,0,0],"id":72,"left_children":[1,3,-1,-1,-1],"loss_changes":[3.3878726E-1,3.01917E-1,0E0,0E0,0E0],"parents":[2147483647,0,0,1,1],"right_children":[2,4,-1,-1,-1],"split_conditions":[2E1,2.2428572E0,-3.888167E-2,-1.9213352E-2,3.3604585E-2],"split_indices":[4,9,0,0,0],"split_type":[0,0,0,0,0],"sum_hessian":[3.5947742E0,2.5505693E0,1.0442048E0,1.0498539E0,1.5007154E0],"tree_param":{"num_deleted":"0","num_feature":"11","num_nodes":"5","size_leaf_vector":"1"}},{"base_weights":[-8.6936995E-2,-3.3930775E-2,2.1647615E-2],"categories":[],"categories_nodes":[],"categories_segments":[],"categories_sizes":[],"default_left":[0,0,0],"id":73,"left_children":[1,-1,-1],"loss_changes":[3.7872532E-1,0E0,0E0],"parents":[2147483647,0,0],"right_children":[2,-1,-1],"split_conditions":[2.1E1,-3.3930775E-2,2.1647615E-2],"split_indices":[1,0,0],"split_type":[0,0,0],"sum_hessian":[2.9867175E0,1.565923E0,1.4207944E0],"tree_param":{"num_deleted":"0","num_feature":"11","num_nodes":"3","size_leaf_vector":"1"}},{"base_weights":[-5.8544908E-2,-4.0995058E-2,2.2466889E-2],"categories":[],"categories_nodes":[],"categories_segments":[],"categories_sizes":[],"default_left":[0,0,0],"id":74,"left_children":[1,-1,-1],"loss_changes":[4.7923705E-1,0E0,0E0],"parents":[2147483647,0,0],"right_children":[2,-1,-1],"split_conditions":[3E0,-4.0995058E-2,2.2466889E-2],"split_indices":[2,0,0],"split_type":[0,0,0],"sum_hessian":[2.8898969E0,1.089979E0,1.7999178E0],"tree_param":{"num_deleted":"0","num_feature":"11","num_nodes":"3","size_leaf_vector":"1"}},{"base_weights":[-4.559293E-2,-3.1330843E-2,2.0625181E-2],"categories":[],"categories_nodes":[],"categories_segments":[],"categories_sizes":[],"default_left":[0,0,0],"id":75,"left_children":[1,-1,-1],"loss_changes":[3.634575E-1,0E0,0E0],"parents":[2147483647,0,0],"right_children":[2,-1,-1],"split_conditions":[1.2E1,-3.1330843E-2,2.0625181E-2],"split_indices":[1,0,0],"split_type":[0,0,0],"sum_hessian":[3.4322894E0,1.5454229E0,1.8868663E0],"tree_param":{"num_deleted":"0","num_feature":"11","num_nodes":"3","size_leaf_vector":"1"}},{"base_weights":[-8.842686E-2,-3.4563832E-2,1.405882E-2],"categories":[],"categories_nodes":[],"categories_segments":[],"categories_sizes":[],"default_left":[0,0,0],"id":76,"left_children":[1,-1,-1],"loss_changes":[2.8203285E-1,0E0,0E0],"parents":[2147483647,0,0],"right_children":[2,-1,-1],"split_conditions":[3E0,-3.4563832E-2,1.405882E-2],"split_indices":[2,0,0],"split_type":[0,0,0],"sum_hessian":[2.962974E0,1.1557215E0,1.8072526E0],"tree_param":{"num_deleted":"0","num_feature":"11","num_nodes":"3","size_leaf_vector":"1"}},{"base_weights":[1.4708789E-1,-2.589058E-2,4.4103123E-2],"categories":[],"categories_nodes":[],"categories_segments":[],"categories_sizes":[],"default_left":[0,0,0],"id":77,"left_children":[1,-1,-1],"loss_changes":[6.124114E-1,0E0,0E0],"parents":[2147483647,0,0],"right_children":[2,-1,-1],"split_conditions":[3E0,-2.589058E-2,4.4103123E-2],"split_indices":[2,0,0],"split_type":[0,0,0],"sum_hessian":[3.1748736E0,1.383368E0,1.7915056E0],"tree_param":{"num_deleted":"0","num_feature":"11","num_nodes":"3","size_leaf_vector":"1"}},{"base_weights":[-9.025112E-2,1.1433776E-1,-3.6421597E-2,-1.603853E-2,3.2417905E-2],"categories":[],"categories_nodes":[],"categories_segments":[],"categories_sizes":[],"default_left":[0,0,0,0,0],"id":78,"left_children":[1,3,-1,-1,-1],"loss_changes":[2.727215E-1,2.3192865E-1,0E0,0E0,0E0],"parents":[2147483647,0,0,1,1],"right_children":[2,4,-1,-1,-1],"split_conditions":[1.19E1,2.2428572E0,-3.6421597E-2,-1.603853E-2,3.2417905E-2],"split_indices":[2,9,0,0,0],"split_type":[0,0,0,0,0],"sum_hessian":[3.1226978E0,2.1212592E0,1.0014386E0,1.0206772E0,1.100582E0],"tree_param":{"num_deleted":"0","num_feature":"11","num_nodes":"5","size_leaf_vector":"1"}},{"base_weights":[-6.713313E-3,1.6876298E-1,-3.0272791E-2,-6.1076777E-3,3.643505E-2],"categories":[],"categories_nodes":[],"categories_segments":[],"categories_sizes":[],"default_left":[0,0,0,0,0],"id":79,"left_children":[1,3,-1,-1,-1],"loss_changes":[3.0425975E-1,1.8867522E-1,0E0,0E0,0E0],"parents":[2147483647,0,0,1,1],"right_children":[2,4,-1,-1,-1],"split_conditions":[1.4E1,6E0,-3.0272791E-2,-6.1076777E-3,3.643505E-2],"split_indices":[4,0,0,0,0],"split_type":[0,0,0,0,0],"sum_hessian":[3.873955E0,2.7020648E0,1.1718904E0,1.5584353E0,1.1436293E0],"tree_param":{"num_deleted":"0","num_feature":"11","num_nodes":"5","size_leaf_vector":"1"}},{"base_weights":[1.0688128E-1,3.8075134E-2,-2.8620346E-2],"categories":[],"categories_nodes":[],"categories_segments":[],"categories_sizes":[],"default_left":[0,0,0],"id":80,"left_children":[1,-1,-1],"loss_changes":[5.290681E-1,0E0,0E0],"parents":[2147483647,0,0],"right_children":[2,-1,-1],"split_conditions":[1.4E1,3.8075134E-2,-2.8620346E-2],"split_indices":[4,0,0],"split_type":[0,0,0],"sum_hessian":[2.9022722E0,1.7290112E0,1.1732612E0],"tree_param":{"num_deleted":"0","num_feature":"11","num_nodes":"3","size_leaf_vector":"1"}},{"base_weights":[1.1682362E-1,3.8232467E-1,-3.6341682E-2,-2.9695344E-3,6.258411E-2],"categories":[],"categories_nodes":[],"categories_segments":[],"categories_sizes":[],"default_left":[0,0,0,0,0],"id":81,"left_children":[1,3,-1,-1,-1],"loss_changes":[6.841574E-1,3.437656E-1,0E0,0E0,0E0],"parents":[2147483647,0,0,1,1],"right_children":[2,4,-1,-1,-1],"split_conditions":[2E1,5.2E0,-3.6341682E-2,-2.9695344E-3,6.258411E-2],"split_indices":[4,0,0,0,0],"split_type":[0,0,0,0,0],"sum_hessian":[3.276044E0,2.240997E0,1.0350468E0,1.1586552E0,1.0823419E0],"tree_param":{"num_deleted":"0","num_feature":"11","num_nodes":"5","size_leaf_vector":"1"}},{"base_weights":[1.6504565E-1,-1.641131E-2,3.2757293E-2],"categories":[],"categories_nodes":[],"categories_segments":[],"categories_sizes":[],"default_left":[0,0,0],"id":82,"left_children":[1,-1,-1],"loss_changes":[2.7082112E-1,0E0,0E0],"parents":[2147483647,0,0],"right_children":[2,-1,-1],"split_conditions":[2.2428572E0,-1.641131E-2,3.2757293E-2],"split_indices":[9,0,0],"split_type":[0,0,0],"sum_hessian":[3.0574415E0,1.0074149E0,2.0500264E0],"tree_param":{"num_deleted":"0","num_feature":"11","num_nodes":"3","size_leaf_vector":"1"}},{"base_weights":[-2.14264E-2,-2.2270514E-2,2.0098174E-2],"categories":[],"categories_nodes":[],"categories_segments":[],"categories_sizes":[],"default_left":[0,0,0],"id":83,"left_children":[1,-1,-1],"loss_changes":[2.4659078E-1,0E0,0E0],"parents":[2147483647,0,0],"right_children":[2,-1,-1],"split_conditions":[5.542857E0,-2.2270514E-2,2.0098174E-2],"split_indices":[9,0,0],"split_type":[0,0,0],"sum_hessian":[3.5085778E0,1.8410748E0,1.667503E0],"tree_param":{"num_deleted":"0","num_feature":"11","num_nodes":"3","size_leaf_vector":"1"}},{"base_weights":[1.410499E-3,-2.0553296E-2,2.0729039E-2],"categories":[],"categories_nodes":[],"categories_segments":[],"categories_sizes":[],"default_left":[0,0,0],"id":84,"left_children":[1,-1,-1],"loss_changes":[2.2368246E-1,0E0,0E0],"parents":[2147483647,0,0],"right_children":[2,-1,-1],"split_conditions":[2.1E1,-2.0553296E-2,2.0729039E-2],"split_indices":[1,0,0],"split_type":[0,0,0],"sum_hessian":[3.2500958E0,1.6217016E0,1.6283942E0],"tree_param":{"num_deleted":"0","num_feature":"11","num_nodes":"3","size_leaf_vector":"1"}},{"base_weights":[-9.804423E-2,-2.8538778E-2,2.0020453E-2],"categories":[],"categories_nodes":[],"categories_segments":[],"categories_sizes":[],"default_left":[0,0,0],"id":85,"left_children":[1,-1,-1],"loss_changes":[2.7275753E-1,0E0,0E0],"parents":[2147483647,0,0],"right_children":[2,-1,-1],"split_conditions":[2.1E1,-2.8538778E-2,2.0020453E-2],"split_indices":[1,0,0],"split_type":[0,0,0],"sum_hessian":[2.8590007E0,1.7824713E0,1.0765294E0],"tree_param":{"num_deleted":"0","num_feature":"11","num_nodes":"3","size_leaf_vector":"1"}},{"base_weights":[-2.5439572E-2,1.47604E-1,-2.937145E-2,-1.5547588E-2,3.4294926E-2],"categories":[],"categories_nodes":[],"categories_segments":[],"categories_sizes":[],"default_left":[0,0,0,0,0],"id":86,"left_children":[1,3,-1,-1,-1],"loss_changes":[2.6008442E-1,2.6074848E-1,0E0,0E0,0E0],"parents":[2147483647,0,0,1,1],"right_children":[2,4,-1,-1,-1],"split_conditions":[2E1,2.2428572E0,-2.937145E-2,-1.5547588E-2,3.4294926E-2],"split_indices":[4,9,0,0,0],"split_type":[0,0,0,0,0],"sum_hessian":[3.668587E0,2.5035453E0,1.1650418E0,1.0611926E0,1.4423527E0],"tree_param":{"num_deleted":"0","num_feature":"11","num_nodes":"5","size_leaf_vector":"1"}},{"base_weights":[1.671629E-2,-1.7954792E-1,2.6130123E-2,2.2751728E-2,-4.9410496E-2],"categories":[],"categories_nodes":[],"categories_segments":[],"categories_sizes":[],"default_left":[0,0,0,0,0],"id":87,"left_children":[1,3,-1,-1,-1],"loss_changes":[2.5749797E-1,4.999527E-1,0E0,0E0,0E0],"parents":[2147483647,0,0,1,1],"right_children":[2,4,-1,-1,-1],"split_conditions":[2.1E1,6.4E0,2.6130123E-2,2.2751728E-2,-4.9410496E-2],"split_indices":[1,1,0,0,0],"split_type":[0,0,0,0,0],"sum_hessian":[3.386824E0,2.0265505E0,1.3602732E0,1.0039955E0,1.0225551E0],"tree_param":{"num_deleted":"0","num_feature":"11","num_nodes":"5","size_leaf_vector":"1"}},{"base_weights":[6.3948676E-2,3.372107E-2,-3.2208573E-2],"categories":[],"categories_nodes":[],"categories_segments":[],"categories_sizes":[],"default_left":[0,0,0],"id":88,"left_children":[1,-1,-1],"loss_changes":[5.142937E-1,0E0,0E0],"parents":[2147483647,0,0],"right_children":[2,-1,-1],"split_conditions":[4E0,3.372107E-2,-3.2208573E-2],"split_indices":[7,0,0],"split_type":[0,0,0],"sum_hessian":[2.8457527E0,1.740313E0,1.1054397E0],"tree_param":{"num_deleted":"0","num_feature":"11","num_nodes":"3","size_leaf_vector":"1"}},{"base_weights":[-6.730257E-2,2.0371875E-2,-2.2304899E-1,-3.2464083E-2,-6.4777076E-4],"categories":[],"categories_nodes":[],"categories_segments":[],"categories_sizes":[],"default_left":[0,0,0,0,0],"id":89,"left_children":[1,-1,3,-1,-1],"loss_changes":[2.2201036E-1,0E0,6.684774E-2,0E0,0E0],"parents":[2147483647,0,0,2,2],"right_children":[2,-1,4,-1,-1],"split_conditions":[5.8E0,2.0371875E-2,1.05E1,-3.2464083E-2,-6.4777076E-4],"split_indices":[0,0,0,0,0],"split_type":[0,0,0,0,0],"sum_hessian":[3.183099E0,1.049245E0,2.133854E0,1.1128314E0,1.0210227E0],"tree_param":{"num_deleted":"0","num_feature":"11","num_nodes":"5","size_leaf_vector":"1"}},{"base_weights":[-5.125793E-2,-2.164326E-2,8.68015E-3],"categories":[],"categories_nodes":[],"categories_segments":[],"categories_sizes":[],"default_left":[0,0,0],"id":90,"left_children":[1,-1,-1],"loss_changes":[1.0666801E-1,0E0,0E0],"parents":[2147483647,0,0],"right_children":[2,-1,-1],"split_conditions":[2.2E0,-2.164326E-2,8.68015E-3],"split_indices":[2,0,0],"split_type":[0,0,0],"sum_hessian":[2.8537822E0,1.0408406E0,1.8129414E0],"tree_param":{"num_deleted":"0","num_feature":"11","num_nodes":"3","size_leaf_vector":"1"}},{"base_weights":[-6.0689836E-3,2.2517882E-2,-2.3832891E-2],"categories":[],"categories_nodes":[],"categories_segments":[],"categories_sizes":[],"default_left":[0,0,0],"id":91,"left_children":[1,-1,-1],"loss_changes":[2.7149183E-1,0E0,0E0],"parents":[2147483647,0,0],"right_children":[2,-1,-1],"split_conditions":[6.3E0,2.2517882E-2,-2.3832891E-2],"split_indices":[2,0,0],"split_type":[0,0,0],"sum_hessian":[3.0556097E0,1.5464182E0,1.5091915E0],"tree_param":{"num_deleted":"0","num_feature":"11","num_nodes":"3","size_leaf_vector":"1"}},{"base_weights":[-1.9422932E-1,-3.1942222E-2,7.778251E-3],"categories":[],"categories_nodes":[],"categories_segments":[],"categories_sizes":[],"default_left":[0,0,0],"id":92,"left_children":[1,-1,-1],"loss_changes":[1.5459803E-1,0E0,0E0],"parents":[2147483647,0,0],"right_children":[2,-1,-1],"split_conditions":[3.17E1,-3.1942222E-2,7.778251E-3],"split_indices":[8,0,0],"split_type":[0,0,0],"sum_hessian":[2.8102062E0,1.8051119E0,1.0050944E0],"tree_param":{"num_deleted":"0","num_feature":"11","num_nodes":"3","size_leaf_vector":"1"}},{"base_weights":[-1.746795E-2,1.7280037E-2,-2.7493253E-2],"categories":[],"categories_nodes":[],"categories_segments":[],"categories_sizes":[],"default_left":[0,0,0],"id":93,"left_children":[1,-1,-1],"loss_changes":[2.4822138E-1,0E0,0E0],"parents":[2147483647,0,0],"right_children":[2,-1,-1],"split_conditions":[2E1,1.7280037E-2,-2.7493253E-2],"split_indices":[4,0,0],"split_type":[0,0,0],"sum_hessian":[3.0972404E0,1.9701344E0,1.1271062E0],"tree_param":{"num_deleted":"0","num_feature":"11","num_nodes":"3","size_leaf_vector":"1"}},{"base_weights":[-6.5297335E-2,1.118821E-1,-3.1763785E-2,-5.4900846E-3,2.3463195E-2],"categories":[],"categories_nodes":[],"categories_segments":[],"categories_sizes":[],"default_left":[0,0,0,0,0],"id":94,"left_children":[1,3,-1,-1,-1],"loss_changes":[2.2899704E-1,8.006467E-2,0E0,0E0,0E0],"parents":[2147483647,0,0,1,1],"right_children":[2,4,-1,-1,-1],"split_conditions":[2E1,2.3857143E0,-3.1763785E-2,-5.4900846E-3,2.3463195E-2],"split_indices":[4,9,0,0,0],"split_type":[0,0,0,0,0],"sum_hessian":[3.3270192E0,2.2816174E0,1.045402E0,1.2016503E0,1.079967E0],"tree_param":{"num_deleted":"0","num_feature":"11","num_nodes":"5","size_leaf_vector":"1"}},{"base_weights":[3.7224762E-2,-2.0343727E-2,1.911566E-1,4.9910784E-2,-2.0614488E-2],"categories":[],"categories_nodes":[],"categories_segments":[],"categories_sizes":[],"default_left":[0,0,0,0,0],"id":95,"left_children":[1,-1,3,-1,-1],"loss_changes":[2.0075592E-1,0E0,4.9201635E-1,0E0,0E0],"parents":[2147483647,0,0,2,2],"right_children":[2,-1,4,-1,-1],"split_conditions":[2.2E0,-2.0343727E-2,1.6E1,4.9910784E-2,-2.0614488E-2],"split_indices":[2,0,2,0,0],"split_type":[0,0,0,0,0],"sum_hessian":[3.36942E0,1.1889582E0,2.180462E0,1.0840005E0,1.0964614E0],"tree_param":{"num_deleted":"0","num_feature":"11","num_nodes":"5","size_leaf_vector":"1"}},{"base_weights":[2.647914E-2,-2.2186624E-2,3.3977736E-2],"categories":[],"categories_nodes":[],"categories_segments":[],"categories_sizes":[],"default_left":[0,0,0],"id":96,"left_children":[1,-1,-1],"loss_changes":[4.0857217E-1,0E0,0E0],"parents":[2147483647,0,0],"right_children":[2,-1,-1],"split_conditions":[2.1E1,-2.2186624E-2,3.3977736E-2],"split_indices":[1,0,0],"split_type":[0,0,0],"sum_hessian":[3.282271E0,1.9937227E0,1.2885482E0],"tree_param":{"num_deleted":"0","num_feature":"11","num_nodes":"3","size_leaf_vector":"1"}},{"base_weights":[-1.347006E-1,1.1936449E-2,-2.7544731E-2],"categories":[],"categories_nodes":[],"categories_segments":[],"categories_sizes":[],"default_left":[0,0,0],"id":97,"left_children":[1,-1,-1],"loss_changes":[1.8099129E-1,0E0,0E0],"parents":[2147483647,0,0],"right_children":[2,-1,-1],"split_conditions":[1.6E1,1.1936449E-2,-2.7544731E-2],"split_indices":[8,0,0],"split_type":[0,0,0],"sum_hessian":[3.1419892E0,1.1742477E0,1.9677415E0],"tree_param":{"num_deleted":"0","num_feature":"11","num_nodes":"3","size_leaf_vector":"1"}},{"base_weights":[1.5132014E-1,2.6735157E-2,-3.554839E-3],"categories":[],"categories_nodes":[],"categories_segments":[],"categories_sizes":[],"default_left":[0,0,0],"id":98,"left_children":[1,-1,-1],"loss_changes":[9.010286E-2,0E0,0E0],"parents":[2147483647,0,0],"right_children":[2,-1,-1],"split_conditions":[7.8E0,2.6735157E-2,-3.554839E-3],"split_indices":[0,0,0],"split_type":[0,0,0],"sum_hessian":[2.7172134E0,1.4106262E0,1.3065872E0],"tree_param":{"num_deleted":"0","num_feature":"11","num_nodes":"3","size_leaf_vector":"1"}},{"base_weights":[8.527419E-2,-1.2456531E-2,2.434434E-2],"categories":[],"categories_nodes":[],"categories_segments":[],"categories_sizes":[],"default_left":[0,0,0],"id":99,"left_children":[1,-1,-1],"loss_changes":[1.5854117E-1,0E0,0E0],"parents":[2147483647,0,0],"right_children":[2,-1,-1],"split_conditions":[3E0,-1.2456531E-2,2.434434E-2],"split_indices":[2,0,0],"split_type":[0,0,0],"sum_hessian":[2.863092E0,1.3218625E0,1.5412295E0],"tree_param":{"num_deleted":"0","num_feature":"11","num_nodes":"3","size_leaf_vector":"1"}}]},"name":"gbtree"},"learner_model_param":{"base_score":"[7.34375E-1]","boost_from_average":"1","num_class":"0","num_feature":"11","num_target":"1"},"objective":{"name":"binary:logistic","reg_loss_param":{"scale_pos_weight":"1"}}},"version":[3,2,0]}